{"nodes": [{"id": "d_github_cleanarchitecturewithblazorserver_src_application_common_security_permissions_roles_cs", "label": "Roles.cs", "file_type": "code", "source_file": "D:\\github\\CleanArchitectureWithBlazorServer\\src\\Application\\Common\\Security\\Permissions\\Roles.cs", "source_location": "L1"}, {"id": "permissions_roles_permissions", "label": "Permissions", "file_type": "code", "source_file": "D:\\github\\CleanArchitectureWithBlazorServer\\src\\Application\\Common\\Security\\Permissions\\Roles.cs", "source_location": "L6"}, {"id": "permissions_roles_roles", "label": "Roles", "file_type": "code", "source_file": "D:\\github\\CleanArchitectureWithBlazorServer\\src\\Application\\Common\\Security\\Permissions\\Roles.cs", "source_location": "L8"}, {"id": "string", "label": "string", "file_type": "code", "source_file": "D:\\github\\CleanArchitectureWithBlazorServer\\src\\Application\\Common\\Security\\Permissions\\Roles.cs", "source_location": "L12"}, {"id": "permissions_roles_rolesaccessrights", "label": "RolesAccessRights", "file_type": "code", "source_file": "D:\\github\\CleanArchitectureWithBlazorServer\\src\\Application\\Common\\Security\\Permissions\\Roles.cs", "source_location": "L52"}], "edges": [{"source": "d_github_cleanarchitecturewithblazorserver_src_application_common_security_permissions_roles_cs", "target": "permissions_roles_permissions", "relation": "contains", "confidence": "EXTRACTED", "source_file": "D:\\github\\CleanArchitectureWithBlazorServer\\src\\Application\\Common\\Security\\Permissions\\Roles.cs", "source_location": "L6", "weight": 1.0}, {"source": "d_github_cleanarchitecturewithblazorserver_src_application_common_security_permissions_roles_cs", "target": "permissions_roles_roles", "relation": "contains", "confidence": "EXTRACTED", "source_file": "D:\\github\\CleanArchitectureWithBlazorServer\\src\\Application\\Common\\Security\\Permissions\\Roles.cs", "source_location": "L8", "weight": 1.0}, {"source": "permissions_roles_roles", "target": "string", "relation": "references", "confidence": "EXTRACTED", "source_file": "D:\\github\\CleanArchitectureWithBlazorServer\\src\\Application\\Common\\Security\\Permissions\\Roles.cs", "source_location": "L12", "weight": 1.0, "context": "field"}, {"source": "permissions_roles_roles", "target": "string", "relation": "references", "confidence": "EXTRACTED", "source_file": "D:\\github\\CleanArchitectureWithBlazorServer\\src\\Application\\Common\\Security\\Permissions\\Roles.cs", "source_location": "L15", "weight": 1.0, "context": "field"}, {"source": "permissions_roles_roles", "target": "string", "relation": "references", "confidence": "EXTRACTED", "source_file": "D:\\github\\CleanArchitectureWithBlazorServer\\src\\Application\\Common\\Security\\Permissions\\Roles.cs", "source_location": "L18", "weight": 1.0, "context": "field"}, {"source": "permissions_roles_roles", "target": "string", "relation": "references", "confidence": "EXTRACTED", "source_file": "D:\\github\\CleanArchitectureWithBlazorServer\\src\\Application\\Common\\Security\\Permissions\\Roles.cs", "source_location": "L21", "weight": 1.0, "context": "field"}, {"source": "permissions_roles_roles", "target": "string", "relation": "references", "confidence": "EXTRACTED", "source_file": "D:\\github\\CleanArchitectureWithBlazorServer\\src\\Application\\Common\\Security\\Permissions\\Roles.cs", "source_location": "L24", "weight": 1.0, "context": "field"}, {"source": "permissions_roles_roles", "target": "string", "relation": "references", "confidence": "EXTRACTED", "source_file": "D:\\github\\CleanArchitectureWithBlazorServer\\src\\Application\\Common\\Security\\Permissions\\Roles.cs", "source_location": "L27", "weight": 1.0, "context": "field"}, {"source": "permissions_roles_roles", "target": "string", "relation": "references", "confidence": "EXTRACTED", "source_file": "D:\\github\\CleanArchitectureWithBlazorServer\\src\\Application\\Common\\Security\\Permissions\\Roles.cs", "source_location": "L29", "weight": 1.0, "context": "field"}, {"source": "permissions_roles_roles", "target": "string", "relation": "references", "confidence": "EXTRACTED", "source_file": "D:\\github\\CleanArchitectureWithBlazorServer\\src\\Application\\Common\\Security\\Permissions\\Roles.cs", "source_location": "L32", "weight": 1.0, "context": "field"}, {"source": "permissions_roles_roles", "target": "string", "relation": "references", "confidence": "EXTRACTED", "source_file": "D:\\github\\CleanArchitectureWithBlazorServer\\src\\Application\\Common\\Security\\Permissions\\Roles.cs", "source_location": "L35", "weight": 1.0, "context": "field"}, {"source": "permissions_roles_roles", "target": "string", "relation": "references", "confidence": "EXTRACTED", "source_file": "D:\\github\\CleanArchitectureWithBlazorServer\\src\\Application\\Common\\Security\\Permissions\\Roles.cs", "source_location": "L38", "weight": 1.0, "context": "field"}, {"source": "permissions_roles_roles", "target": "string", "relation": "references", "confidence": "EXTRACTED", "source_file": "D:\\github\\CleanArchitectureWithBlazorServer\\src\\Application\\Common\\Security\\Permissions\\Roles.cs", "source_location": "L41", "weight": 1.0, "context": "field"}, {"source": "permissions_roles_roles", "target": "string", "relation": "references", "confidence": "EXTRACTED", "source_file": "D:\\github\\CleanArchitectureWithBlazorServer\\src\\Application\\Common\\Security\\Permissions\\Roles.cs", "source_location": "L44", "weight": 1.0, "context": "field"}, {"source": "permissions_roles_roles", "target": "string", "relation": "references", "confidence": "EXTRACTED", "source_file": "D:\\github\\CleanArchitectureWithBlazorServer\\src\\Application\\Common\\Security\\Permissions\\Roles.cs", "source_location": "L47", "weight": 1.0, "context": "field"}, {"source": "d_github_cleanarchitecturewithblazorserver_src_application_common_security_permissions_roles_cs", "target": "permissions_roles_rolesaccessrights", "relation": "contains", "confidence": "EXTRACTED", "source_file": "D:\\github\\CleanArchitectureWithBlazorServer\\src\\Application\\Common\\Security\\Permissions\\Roles.cs", "source_location": "L52", "weight": 1.0}], "raw_calls": []}